lightmus/__init__.py
lightmus/__main__.py
lightmus/cli.py
lightmus/discovery.py
lightmus/introspection.py
lightmus/models.py
lightmus/reporting.py
lightmus/runner.py
lightmus-0.1.1.dist-info/METADATA
lightmus-0.1.1.dist-info/WHEEL
lightmus-0.1.1.dist-info/entry_points.txt
lightmus-0.1.1.dist-info/RECORD
