Metadata-Version: 2.4
Name: lightmus
Version: 0.1.1
Summary: A minimal pytest-like testing framework
Project-URL: Repository, https://github.com/lightmus/lightmus
Author: Lightmus Contributors
License-Expression: MIT
Keywords: framework,pytest,test,testing
Classifier: Development Status :: 3 - Alpha
Classifier: Environment :: Console
Classifier: Intended Audience :: Developers
Classifier: License :: OSI Approved :: MIT License
Classifier: Operating System :: OS Independent
Classifier: Programming Language :: Python :: 3
Classifier: Programming Language :: Python :: 3.11
Classifier: Programming Language :: Python :: 3.12
Classifier: Topic :: Software Development :: Testing
Requires-Python: >=3.11
